ckanext_ids-1.1.0-py3.10-nspkg.pth
ckanext/ids/__init__.py
ckanext/ids/activity.py
ckanext/ids/blueprints.py
ckanext/ids/harvester.py
ckanext/ids/helpers.py
ckanext/ids/plugin.py
ckanext/ids/swagger.py
ckanext/ids/test.py
ckanext/ids/usage_control.json
ckanext/ids/validator.py
ckanext/ids/assets/resource.config
ckanext/ids/assets/webassets.yml
ckanext/ids/assets/css/resource-upload.css
ckanext/ids/assets/js/resource-upload.js
ckanext/ids/dataspaceconnector/__init__.py
ckanext/ids/dataspaceconnector/connector.py
ckanext/ids/dataspaceconnector/contract.py
ckanext/ids/dataspaceconnector/idsapi.py
ckanext/ids/dataspaceconnector/offer.py
ckanext/ids/dataspaceconnector/resource.py
ckanext/ids/dataspaceconnector/resourceapi.py
ckanext/ids/dataspaceconnector/subscribe.py
ckanext/ids/dataspaceconnector/subscriptionapi.py
ckanext/ids/i18n/ckanext-ids.pot
ckanext/ids/i18n/en/LC_MESSAGES/ckanext-ids.po
ckanext/ids/logic/__init__.py
ckanext/ids/logic/action.py
ckanext/ids/metadatabroker/__init__.py
ckanext/ids/metadatabroker/client.py
ckanext/ids/metadatabroker/translations_broker_ckan.py
ckanext/ids/model/__init__.py
ckanext/ids/public/api/swagger/ckan_ids_openapi.json
ckanext/ids/public/api/swagger/ckan_ids_openapi.yaml
ckanext/ids/public/images/TrustsLogo.png
ckanext/ids/recomm/__init__.py
ckanext/ids/recomm/recomm.py
ckanext/ids/schemes/application.yml
ckanext/ids/schemes/dataset.yml
ckanext/ids/schemes/organization.yml
ckanext/ids/schemes/presets.json
ckanext/ids/schemes/service.yml
ckanext/ids/smart_contracts/__init__.py
ckanext/ids/smart_contracts/smart_contract_client.py
ckanext/ids/templates/base.html
ckanext/ids/templates/header.html
ckanext/ids/templates/index.template.html
ckanext/ids/templates/admin/config.html
ckanext/ids/templates/form-snippets/slug.html
ckanext/ids/templates/macros/custom_form.html
ckanext/ids/templates/organization/read.html
ckanext/ids/templates/organization/snippets/organization_item.html
ckanext/ids/templates/package/base_form_page.html
ckanext_ids-1.1.0.dist-info/LICENSE
ckanext_ids-1.1.0.dist-info/METADATA
ckanext_ids-1.1.0.dist-info/WHEEL
ckanext_ids-1.1.0.dist-info/entry_points.txt
ckanext_ids-1.1.0.dist-info/namespace_packages.txt
ckanext_ids-1.1.0.dist-info/top_level.txt
ckanext_ids-1.1.0.dist-info/RECORD
