Metadata-Version: 2.1
Name: ckanext-ids
Version: 1.1.0
Summary: IDS data model extension for CKAN
Home-page: https://github.com/semantic-web-company/ckanext-ids
Author: Sotiris Karampatakis
Author-email: sotiris.karampatakis@semantic-web.com
License: AGPL
Keywords: CKAN IDS
Classifier: Development Status :: 3 - Alpha
Classifier: License :: OSI Approved :: GNU Affero General Public License v3 or later (AGPLv3+)
Classifier: Programming Language :: Python :: 3.7
License-File: LICENSE
